lonny_common_pg_migrate/__init__.py
lonny_common_pg_migrate/cfg.py
lonny_common_pg_migrate/cli.py
lonny_common_pg_migrate/logger.py
lonny_common_pg_migrate/runner.py
lonny_common_pg_migrate-0.1.1.dist-info/entry_points.txt
lonny_common_pg_migrate-0.1.1.dist-info/LICENSE
lonny_common_pg_migrate-0.1.1.dist-info/WHEEL
lonny_common_pg_migrate-0.1.1.dist-info/METADATA
lonny_common_pg_migrate-0.1.1.dist-info/RECORD
